[
 {
  "type": "database",
  "name": "projeto_integrador"
 },
 {
  "type": "table",
  "name": "produto",
  "database": "projeto_integrador",
  "data": [
   {
    "id": "1",
    "nome": "Jogo FarCry Xbox",
    "preco": "150.00",
    "img": "./public/img/farcry.jpg",
    "description": "Jogo de tiro e ação, FPS, Xbox One"
   },
   {
    "id": "2",
    "nome": "Jogo Grand Playstation",
    "preco": "89.90",
    "img": "./public/img/granturismo.jpg",
    "description": "Jogo Gran Turismo Xbox. Importado dos EUA. Entregue com a fatura de compra para ter a garantia do fabricante."
   },
   {
    "id": "3",
    "nome": "Jogo Mortal Kombat PlayStation",
    "preco": "359.90",
    "img": "./public/img/mortal.jpg",
    "description": "Jogo Mortal Kombat PlayStation. Experiência excepcional de visualização."
   },
   {
    "id": "4",
    "nome": "Xbox One",
    "preco": "999.99",
    "img": "./public/img/xbox.jpg",
    "description": "Xbox One X. Lançamento 2020."
   },
   {
    "id": "5",
    "nome": "Controle Xbox",
    "preco": "399.90",
    "img": "./public/img/controlexo.jpg",
    "description": "Controle Xbox One sem fio, garantia de 1 ano"
   },
   {
    "id": "6",
    "nome": "Jogo Marvel 3 Xbox",
    "preco": "150.00",
    "img": "./public/img/marvel.jpg",
    "description": "Jogo Xbox Marvel para faixa etária a partir dos 04 anos de idade."
   }
  ]
 }
]